sysexpert/__init__.py
sysexpert/analyseursyntaxique.py
sysexpert/basedefaits.py
sysexpert/basederegles.py
sysexpert/cli.py
sysexpert/fait.py
sysexpert/gui.py
sysexpert/gui_colorationsyntax.py
sysexpert/gui_dialog.py
sysexpert/gui_terminal.py
sysexpert/log.py
sysexpert/moteurdinference.py
sysexpert/proposition.py
sysexpert/regle.py
sysexpert/type.py
sysexpert/res/fonts/OverpassMono-Bold.ttf
sysexpert/res/fonts/OverpassMono-Light.ttf
sysexpert/res/fonts/OverpassMono-Regular.ttf
sysexpert/res/fonts/OverpassMono-SemiBold.ttf
sysexpert/res/html/aide_fichier.html
sysexpert/res/html/aide_terminal.html
sysexpert/res/html/apropos.html
sysexpert/res/icons/app.svg
sysexpert/res/icons/baseline-announcement-24px.svg
sysexpert/res/icons/baseline-arrow_back-24px.svg
sysexpert/res/icons/baseline-arrow_forward-24px.svg
sysexpert/res/icons/baseline-clear-24px.svg
sysexpert/res/icons/baseline-exit_to_app-24px.svg
sysexpert/res/icons/baseline-help-24px.svg
sysexpert/res/icons/baseline-library_add-24px.svg
sysexpert/res/icons/baseline-refresh-24px.svg
sysexpert/res/icons/baseline-settings-20px.svg
sysexpert-0.2.dist-info/LICENSE.txt
sysexpert-0.2.dist-info/METADATA
sysexpert-0.2.dist-info/WHEEL
sysexpert-0.2.dist-info/entry_points.txt
sysexpert-0.2.dist-info/top_level.txt
sysexpert-0.2.dist-info/RECORD
