Metadata-Version: 2.1
Name: sysexpert
Version: 0.2
Summary: Systeme Expert 0+
Home-page: https://github.com/theodeze/SystemeExpert
Author: Théo Dézé, Charles Mallet
Author-email: theo.deze@etud.univ-angers.fr, charles.mallet@etud.univ-angers.fr
License: LICENSE.txt
Platform: UNKNOWN
Requires-Python: >=3
Requires-Dist: pptree (>=2.0)
Requires-Dist: pyside2 (>=5.9.0)
